panda_robot_server/__about__.py
panda_robot_server/__init__.py
panda_robot_server-0.0.0.dist-info/METADATA
panda_robot_server-0.0.0.dist-info/WHEEL
panda_robot_server-0.0.0.dist-info/licenses/LICENSE
panda_robot_server-0.0.0.dist-info/RECORD
