Metadata-Version: 2.1
Name: panda-robot-server
Version: 0.0.0
Summary: Web Server to control the Franka Emika Panda robot.
Project-URL: Homepage, https://github.com/williamshen-nz/panda-robot-server
Author-email: William Shen <willshen@mit.edu>
License-File: LICENSE
Keywords: panda,robotics
Classifier: License :: OSI Approved :: MIT License
Classifier: Programming Language :: Python
Classifier: Programming Language :: Python :: 3.8
Requires-Python: >=3.8
Requires-Dist: pybullet
Requires-Dist: pyjwt
Requires-Dist: requests
Requires-Dist: sanic
Provides-Extra: lint
Requires-Dist: black; extra == 'lint'
Requires-Dist: isort; extra == 'lint'
Requires-Dist: mypy; extra == 'lint'
Provides-Extra: tests
Requires-Dist: pytest; extra == 'tests'
Requires-Dist: pytest-cov; extra == 'tests'
